target_kbc
