Metadata-Version: 1.1
Name: target-kbc
Version: 0.1.4
Summary: Singer.io target for importing data into KBC
Home-page: https://bitbucket.org/chanleoc/target-keboola
Author: Leo
Author-email: cleojanten@hotmail.com
License: MIT
Platform: UNKNOWN
Classifier: Programming Language :: Python :: 3 :: Only
